[
  {
    "id": "oil_flamethrower",
    "copy-from": "flamethrower_base",
    "looks_like": "flamethrower",
    "type": "GUN",
    "name": { "str": "Oil-powered flamethrower" },
    "description": "A makeshift flamethrower that uses crude oil as fuel. It's less efficient than military models but can be crafted from scavenged parts. The oil burns hot and sticky, making it effective against groups of enemies.",
    "weight": "12000 g",
    "volume": "75000 ml",
    "longest_side": "600 mm",
    "price": 50000,
    "price_postapoc": 3000,
    "to_hit": -2,
    "range": 5,
    "dispersion": 400,
    "durability": 6,
    "modes": [ [ "DEFAULT", "Jet", 1 ], [ "AUTO", "Spray", 3 ] ],
    "skill": "launcher",
    "extend": { "flags": [ "BELTED", "ONLY_ONE", "PRIMITIVE_RANGED_WEAPON", "IS_ARMOR" ] },
    "armor_data": {
      "armor": [
        {
          "material": [
            { "type": "steel", "covered_by_mat": 60, "thickness": 2 },
            { "type": "plastic", "covered_by_mat": 100, "thickness": 1 }
          ],
          "volume_encumber_modifier": 0.25,
          "encumbrance": [ 0, 65 ],
          "coverage": 75,
          "covers": [ "torso" ],
          "specifically_covers": [ "torso_hanging_back" ]
        }
      ]
    },
    "valid_mod_locations": [ [ "rail mount", 1 ], [ "grip", 1 ], [ "sights mount", 1 ], [ "stock mount", 1 ], [ "underbarrel mount", 1 ] ],
    "ammo": [ "fluid_crude_oil" ],
    "pocket_data": [
      {
        "pocket_type": "MAGAZINE",
        "watertight": true,
        "rigid": true,
        "ammo_restriction": { "fluid_crude_oil": 1000 }
      }
    ],
    "melee_damage": { "bash": 8 }
  },
  {
    "id": "oil_flamethrower_fuel",
    "type": "AMMO",
    "name": { "str_sp": "crude oil fuel mix" },
    "description": "A mixture of crude oil and additives that can be used as flamethrower fuel. It's thick and burns with a heavy, sooty flame.",
    "category": "fuel",
    "weight": "750 mg",
    "volume": "200 ml",
    "count": 250,
    "stack_size": 200,
    "price": 100,
    "price_postapoc": 50,
    "phase": "liquid",
    "container": "jerrycan",
    "material": [ "fluid_crude_oil" ],
    "symbol": "~",
    "color": "dark_gray",
    "ammo_type": "fluid_crude_oil",
    "damage": {
      "damage_type": "heat",
      "amount": 6,
      "armor_penetration": 3
    },
    "range": 5,
    "effects": [
      "FLAME",
      "STREAM",
      "INCENDIARY",
      "NEVER_MISFIRES"
    ]
  },
  {
    "id": "oil_derrick_item",
    "type": "TOOL",
    "name": { "str": "Oil derrick" },
    "description": "Complex artisanal structure for extracting crude oil, folded up for transport.",
    "weight": "250 kg",
    "volume": "500 L",
    "symbol": "T",
    "color": "dark_gray",
    "material": [ "steel" ],
    "flags": [ "NO_UNLOAD", "ALWAYS_TWOHAND" ]
  },
{
    "id": "fluid_crude_oil",
    "type": "AMMO",
    "name": {
      "str": "Crude oil"
    },
    "description": "Thick, black, oily liquid. Can be processed into fuel.",
    "category": "fuel",
    "weight": "750 mg",
    "volume": "200 ml",
    "count": 250,
    "stack_size": 200,
    "price": 0,
    "price_postapoc": 0,
    "phase": "liquid",
    "container": "jerrycan",
    "material": [
      "fluid_crude_oil"
    ],
    "symbol": "~",
    "color": "dark_gray",
    "ammo_type": "fluid_crude_oil",
    "damage": {
      "damage_type": "heat",
      "amount": 5,
      "armor_penetration": 5
    },
  "range": 4,
  "effects": [
    "FLAME",
    "STREAM",
    "INCENDIARY",
    "NEVER_MISFIRES"
  ]
},
 {
  "type": "TOOL",
  "id": "fake_oil_derrick",
  "name": {
    "str": "Oil derrick (fake object)"
  },
  "description": "Technical fake tool.",
  "flags": [
    "ZERO_WEIGHT",
    "DEBUG_ONLY"
  ],
  "weight": "1 g",
  "volume": "1 ml",
  "symbol": "T",
  "color": "dark_gray",
  "qualities": [
    [ "OIL_PUMP", 1 ]
  ]
},
{
    "id": "oil_pump_tool_corded",
    "type": "TOOL",
    "name": {
      "str": "Pump for an oil derrick"
    },
    "description": "Portable electric pump for oil derricks.",
    "weight": "20000 g",
    "volume": "10 L",
    "price": "1000 USD",
    "material": [
      "steel",
      "plastic"
    ],
    "symbol": "{",
    "color": "light_gray",
    "ammo": [
      "battery"
    ],
    "charges_per_use": 500,
    "use_action": [
      {
        "type": "link_up",
        "cable_length": 12,
        "charge_rate": "36000 W"
      }
    ],
    "flags": [
      "NONCONDUCTIVE"
    ],
    "melee_damage": {
      "bash": 5
    }
  },
{
    "id": "oil_refinery_item",
    "type": "TOOL",
    "name": { "str": "Furnace for oil distillation" },
    "description": "Furnace for distilling oil into various types of fuel.",
    "weight": "350 kg",
    "volume": "400 L",
    "symbol": "R",
    "color": "light_gray",
    "material": [ "steel" ],
    "flags": [ "NO_UNLOAD", "ALWAYS_TWOHAND" ]
  },
{
  "type": "TOOL",
  "name": {
    "str": "Furnace for oil distillation (fake object)"
  },
  "description": "Technical fake instrument.",
  "flags": [
    "ZERO_WEIGHT",
    "DEBUG_ONLY"
  ],
  "weight": "1 g",
  "volume": "1 ml",
  "symbol": "@",
  "color": "red",
  "id": "fake_oil_refinery",
  "qualities": [
    [ "DISTILL", 3 ],
    [ "COOK", 2 ],
    [ "CONTAIN", 2 ]
  ]
},
{
  "id": "oil_refinery_heater",
  "type": "TOOL",
  "name": {
    "str": "Heating elements for oil distillation furnace"
  },
  "description": "Powerful portable electric heating elements for heating furnace during oil distillation.",
  "weight": "15 kg",
  "volume": "10 L",
  "price": 3500,
  "price_postapoc": 200,
  "symbol": "E",
  "color": "red",
  "material": [ "steel", "copper" ],
  "flags": [ 
    "NO_UNLOAD",
    "ALWAYS_TWOHAND"
  ],
  "use_action": [
    {
      "type": "link_up",
      "cable_length": 4,
      "charge_rate": "10000 W"
    }
  ]
},
{
  "id": "fuel_oil",
  "type": "AMMO",
  "name": {
    "str": "fuel oil"
  },
  "description": "Thick, dark, heavy fraction of oil.",
  "category": "fuel",
  "weight": "750 mg",
  "volume": "200 ml",
  "count": 250,
  "stack_size": 200,
  "price": 0,
  "price_postapoc": 0,
  "phase": "liquid",
  "container": "jerrycan",
  "material": [
    "fuel_oil"
  ],
  "symbol": "~",
  "color": "dark_gray",
  "ammo_type": "fuel_oil"
}

]

